functions/__init__.py
functions/core.py
functions/test_core.py
random_functions_lib-0.1.8.dist-info/licenses/LICENSE
random_functions_lib-0.1.8.dist-info/METADATA
random_functions_lib-0.1.8.dist-info/WHEEL
random_functions_lib-0.1.8.dist-info/top_level.txt
random_functions_lib-0.1.8.dist-info/RECORD
