Metadata-Version: 2.4
Name: random_functions_lib
Version: 0.1.8
Summary: a bunch of functions
Home-page: 
Author: Cove Allen
License: MIT
License-File: LICENSE
Dynamic: author
Dynamic: license
Dynamic: license-file
Dynamic: summary
